replyify_oauth2/__init__.py
replyify_oauth2/admin.py
replyify_oauth2/apps.py
replyify_oauth2/decorators.py
replyify_oauth2/models.py
replyify_oauth2/settings.py
replyify_oauth2/urls.py
replyify_oauth2/utils.py
replyify_oauth2/views.py
replyify_oauth2/migrations/0001_initial.py
replyify_oauth2/migrations/__init__.py
django_replyify_oauth2-0.3.0.dist-info/LICENSE
django_replyify_oauth2-0.3.0.dist-info/METADATA
django_replyify_oauth2-0.3.0.dist-info/WHEEL
django_replyify_oauth2-0.3.0.dist-info/top_level.txt
django_replyify_oauth2-0.3.0.dist-info/RECORD
