Metadata-Version: 2.1
Name: django-replyify-oauth2
Version: 0.3.0
Summary: Replyify OAuth2 consumer for Django
Home-page: https://replyify.com
Author: Replyify
Author-email: team@replyify.com
Keywords: replyify,oauth2,django
Classifier: Environment :: Web Environment
Classifier: Framework :: Django
Classifier: Framework :: Django :: 4.0
Classifier: Intended Audience :: Developers
Classifier: License :: OSI Approved :: MIT License
Classifier: Operating System :: OS Independent
Classifier: Programming Language :: Python
Classifier: Programming Language :: Python :: 2
Classifier: Programming Language :: Python :: 3
Classifier: Topic :: Internet :: WWW/HTTP
Classifier: Topic :: Internet :: WWW/HTTP :: Dynamic Content
Requires-Python: ~=3.10
License-File: LICENSE
Requires-Dist: Django >=4.0
Requires-Dist: requests >=0.10.1
